jsonbase.py
jsonbase-10.0.10.dist-info/LICENSE.txt
jsonbase-10.0.10.dist-info/METADATA
jsonbase-10.0.10.dist-info/WHEEL
jsonbase-10.0.10.dist-info/top_level.txt
jsonbase-10.0.10.dist-info/RECORD
